[
    {
        "name": "Alice",
        "text": "This is a sample post.",
        "image": "https://images.pexels.com/photos/27525165/pexels-photo-27525165/free-photo-of-a-woman-laying-down-on-a-piano-with-candles.jpeg?auto=compress&cs=tinysrgb&w=600&lazy=load",
        "video": ""
    },
    {
        "name": "Bob",
        "text": "Another example post.",
        "image": "",
        "video": "./vid1.mp4"
    },
    {
        "name": "Charlie",
        "text": "Just a text post.",
        "image": "",
        "video": "./vid2.mp4"
    },
    {
        "name": "Diana",
        "text": "A beautiful sunrise!",
        "image": "https://images.pexels.com/photos/27495830/pexels-photo-27495830/free-photo-of-sophisticated-lifestyle-setting-with-jewelry-and-magazine.jpeg?auto=compress&cs=tinysrgb&w=600&lazy=load",
        "video": ""
    },
    {
        "name": "Edward",
        "text": "Check out this cool video!",
        "image": "",
        "video": "./assets/reel.mp4"
    },
    {
        "name": "Fiona",
        "text": "Had a great day at the beach.",
        "image": "",
        "video": "./assets/rel.mp4"
    },
    {
        "name": "George",
        "text": "Here's a quick video tutorial.",
        "image": "",
        "video": "./assets/best.mp4"
    },
    {
        "name": "Hannah",
        "text": "A day in the life.",
        "image": "https://images.pexels.com/photos/7704832/pexels-photo-7704832.jpeg?auto=compress&cs=tinysrgb&w=600&lazy=load",
        "video": ""
    },
    {
        "name": "Hannah",
        "text": "A day in the life.",
        "image": "https://images.pexels.com/photos/7704832/pexels-photo-7704832.jpeg?auto=compress&cs=tinysrgb&w=600&lazy=load",
        "video": ""
    },
    {
        "name": "Hannah",
        "text": "A day in the life.",
        "image": "https://images.pexels.com/photos/7704832/pexels-photo-7704832.jpeg?auto=compress&cs=tinysrgb&w=600&lazy=load",
        "video": ""
    },
    {
        "name": "Hannah",
        "text": "A day in the life.",
        "image": "https://images.pexels.com/photos/7704832/pexels-photo-7704832.jpeg?auto=compress&cs=tinysrgb&w=600&lazy=load",
        "video": ""
    },
    {
        "name": "Hannah",
        "text": "A day in the life.",
        "image": "https://images.pexels.com/photos/7704832/pexels-photo-7704832.jpeg?auto=compress&cs=tinysrgb&w=600&lazy=load",
        "video": ""
    },
    {
        "name": "Hannah",
        "text": "A day in the life.",
        "image": "https://images.pexels.com/photos/7704832/pexels-photo-7704832.jpeg?auto=compress&cs=tinysrgb&w=600&lazy=load",
        "video": ""
    },
    {
        "name": "Hannah",
        "text": "A day in the life.",
        "image": "https://images.pexels.com/photos/7704832/pexels-photo-7704832.jpeg?auto=compress&cs=tinysrgb&w=600&lazy=load",
        "video": ""
    },
    {
        "name": "Hannah",
        "text": "A day in the life.",
        "image": "https://images.pexels.com/photos/7704832/pexels-photo-7704832.jpeg?auto=compress&cs=tinysrgb&w=600&lazy=load",
        "video": ""
    },
    {
        "name": "Hannah",
        "text": "A day in the life.",
        "image": "https://images.pexels.com/photos/7704832/pexels-photo-7704832.jpeg?auto=compress&cs=tinysrgb&w=600&lazy=load",
        "video": ""
    },
    {
        "name": "Hannah",
        "text": "A day in the life.",
        "image": "https://images.pexels.com/photos/7704832/pexels-photo-7704832.jpeg?auto=compress&cs=tinysrgb&w=600&lazy=load",
        "video": ""
    },
    {
        "name": "Hannah",
        "text": "A day in the life.",
        "image": "https://images.pexels.com/photos/7704832/pexels-photo-7704832.jpeg?auto=compress&cs=tinysrgb&w=600&lazy=load",
        "video": ""
    },
    {
        "name": "Hannah",
        "text": "A day in the life.",
        "image": "https://images.pexels.com/photos/7704832/pexels-photo-7704832.jpeg?auto=compress&cs=tinysrgb&w=600&lazy=load",
        "video": ""
    },
    {
        "name": "Hannah",
        "text": "A day in the life.",
        "image": "https://images.pexels.com/photos/7704832/pexels-photo-7704832.jpeg?auto=compress&cs=tinysrgb&w=600&lazy=load",
        "video": ""
    },
    {
        "name": "Hannah",
        "text": "A day in the life.",
        "image": "https://images.pexels.com/photos/7704832/pexels-photo-7704832.jpeg?auto=compress&cs=tinysrgb&w=600&lazy=load",
        "video": ""
    },
    {
        "name": "Hannah",
        "text": "A day in the life.",
        "image": "https://images.pexels.com/photos/7704832/pexels-photo-7704832.jpeg?auto=compress&cs=tinysrgb&w=600&lazy=load",
        "video": ""
    },
    {
        "name": "Hannah",
        "text": "A day in the life.",
        "image": "https://images.pexels.com/photos/7704832/pexels-photo-7704832.jpeg?auto=compress&cs=tinysrgb&w=600&lazy=load",
        "video": ""
    },
    {
        "name": "Hannah",
        "text": "A day in the life.",
        "image": "https://images.pexels.com/photos/7704832/pexels-photo-7704832.jpeg?auto=compress&cs=tinysrgb&w=600&lazy=load",
        "video": ""
    },
    {
        "name": "Hannah",
        "text": "A day in the life.",
        "image": "https://images.pexels.com/photos/7704832/pexels-photo-7704832.jpeg?auto=compress&cs=tinysrgb&w=600&lazy=load",
        "video": ""
    },
    {
        "name": "Hannah",
        "text": "A day in the life.",
        "image": "https://images.pexels.com/photos/7704832/pexels-photo-7704832.jpeg?auto=compress&cs=tinysrgb&w=600&lazy=load",
        "video": ""
    },
    {
        "name": "Hannah",
        "text": "A day in the life.",
        "image": "https://images.pexels.com/photos/7704832/pexels-photo-7704832.jpeg?auto=compress&cs=tinysrgb&w=600&lazy=load",
        "video": ""
    },
    {
        "name": "Hannah",
        "text": "A day in the life.",
        "image": "https://images.pexels.com/photos/7704832/pexels-photo-7704832.jpeg?auto=compress&cs=tinysrgb&w=600&lazy=load",
        "video": ""
    },
    {
        "name": "Hannah",
        "text": "A day in the life.",
        "image": "https://images.pexels.com/photos/7704832/pexels-photo-7704832.jpeg?auto=compress&cs=tinysrgb&w=600&lazy=load",
        "video": ""
    }
]
